<?xml version="1.0" encoding="utf-8"?>
<mechanism xmlns:xsd="http://www.w3.org/2001/XMLSchema" xmlns:xsi="http://www.w3.org/2001/XMLSchema-instance">
  <GUID>914a71a8-43f1-46b8-9094-1836667e24b0</GUID>
  <name>superIntake</name>
  <MotorControllers>
    <MotorController
      xsi:type="TalonFX">
      <name>leftIntakeMotor</name>
      <canID>
        <unitsFamily>none</unitsFamily>
        <name>canID</name>
        <__units__ />
        <type>UInt32</type>
        <value>0</value>
      </canID>
      <pdpID>
        <unitsFamily>none</unitsFamily>
        <name>pdpID</name>
        <__units__ />
        <type>UInt32</type>
        <value>0</value>
      </pdpID>
      <followID>
        <unitsFamily>none</unitsFamily>
        <name>followID</name>
        <__units__ />
        <type>UInt32</type>
        <value>0</value>
      </followID>
      <enableFollowID>
        <unitsFamily>none</unitsFamily>
        <name>enableFollowID</name>
        <__units__ />
        <type>Boolean</type>
        <value>false</value>
      </enableFollowID>
      <theMotorConfigs>
        <deadbandPercent>
          <unitsFamily>percent</unitsFamily>
          <name>deadbandPercent</name>
          <__units__>%</__units__>
          <type>Double</type>
          <value>0</value>
        </deadbandPercent>
        <peakMin>
          <unitsFamily>current</unitsFamily>
          <name>peakMin</name>
          <__units__>A</__units__>
          <type>Double</type>
          <value>0</value>
        </peakMin>
        <peakMax>
          <unitsFamily>current</unitsFamily>
          <name>peakMax</name>
          <__units__>A</__units__>
          <type>Double</type>
          <value>0</value>
        </peakMax>
      </theMotorConfigs>
      <theCurrentLimits>
        <enableStatorCurrentLimit>
          <unitsFamily>none</unitsFamily>
          <name>enableStatorCurrentLimit</name>
          <__units__ />
          <type>Boolean</type>
          <value>false</value>
        </enableStatorCurrentLimit>
        <statorCurrentLimit>
          <unitsFamily>current</unitsFamily>
          <name>statorCurrentLimit</name>
          <__units__>A</__units__>
          <type>Double</type>
          <value>0</value>
        </statorCurrentLimit>
        <enableSupplyCurrentLimit>
          <unitsFamily>none</unitsFamily>
          <name>enableSupplyCurrentLimit</name>
          <__units__ />
          <type>Boolean</type>
          <value>false</value>
        </enableSupplyCurrentLimit>
        <supplyCurrentLimit>
          <unitsFamily>current</unitsFamily>
          <name>supplyCurrentLimit</name>
          <__units__>A</__units__>
          <type>Double</type>
          <value>0</value>
        </supplyCurrentLimit>
        <supplyCurrentThreshold>
          <unitsFamily>current</unitsFamily>
          <name>supplyCurrentThreshold</name>
          <__units__>A</__units__>
          <type>Double</type>
          <value>0</value>
        </supplyCurrentThreshold>
        <supplyTimeThreshold>
          <unitsFamily>time</unitsFamily>
          <name>supplyTimeThreshold</name>
          <__units__>s</__units__>
          <type>Double</type>
          <value>0</value>
        </supplyTimeThreshold>
      </theCurrentLimits>
      <theVoltageConfigs>
        <peakForwardVoltage>
          <unitsFamily>time</unitsFamily>
          <name>peakForwardVoltage</name>
          <__units__>s</__units__>
          <type>Double</type>
          <value>0</value>
        </peakForwardVoltage>
        <peakReverseVoltage>
          <unitsFamily>time</unitsFamily>
          <name>peakReverseVoltage</name>
          <__units__>s</__units__>
          <type>Double</type>
          <value>0</value>
        </peakReverseVoltage>
        <supplyVoltageTime>
          <unitsFamily>time</unitsFamily>
          <name>supplyVoltageTime</name>
          <__units__>s</__units__>
          <type>Double</type>
          <value>0</value>
        </supplyVoltageTime>
      </theVoltageConfigs>
      <theTorqueConfigs>
        <peakForwardTorqueCurrent>
          <unitsFamily>current</unitsFamily>
          <name>peakForwardTorqueCurrent</name>
          <__units__>A</__units__>
          <type>Double</type>
          <value>0</value>
        </peakForwardTorqueCurrent>
        <peakReverseTorqueCurrent>
          <unitsFamily>current</unitsFamily>
          <name>peakReverseTorqueCurrent</name>
          <__units__>A</__units__>
          <type>Double</type>
          <value>0</value>
        </peakReverseTorqueCurrent>
        <torqueNeutralDeadband>
          <unitsFamily>current</unitsFamily>
          <name>torqueNeutralDeadband</name>
          <__units__>A</__units__>
          <type>Double</type>
          <value>0</value>
        </torqueNeutralDeadband>
      </theTorqueConfigs>
      <theFeedbackConfigs>
        <feedbackRotorOffset>
          <unitsFamily>angle</unitsFamily>
          <name>feedbackRotorOffset</name>
          <__units__>deg</__units__>
          <type>Double</type>
          <value>0</value>
        </feedbackRotorOffset>
        <remoteSensorID>
          <unitsFamily>none</unitsFamily>
          <name>remoteSensorID</name>
          <__units__ />
          <type>Int32</type>
          <value>0</value>
        </remoteSensorID>
      </theFeedbackConfigs>
    </MotorController>
    <MotorController
      xsi:type="TalonFX">
      <name>rightIntakeMotor</name>
      <canID>
        <unitsFamily>none</unitsFamily>
        <name>canID</name>
        <__units__ />
        <type>UInt32</type>
        <value>0</value>
      </canID>
      <pdpID>
        <unitsFamily>none</unitsFamily>
        <name>pdpID</name>
        <__units__ />
        <type>UInt32</type>
        <value>0</value>
      </pdpID>
      <followID>
        <unitsFamily>none</unitsFamily>
        <name>followID</name>
        <__units__ />
        <type>UInt32</type>
        <value>0</value>
      </followID>
      <enableFollowID>
        <unitsFamily>none</unitsFamily>
        <name>enableFollowID</name>
        <__units__ />
        <type>Boolean</type>
        <value>false</value>
      </enableFollowID>
      <motor>Kraken</motor>
      <theMotorConfigs>
        <deadbandPercent>
          <unitsFamily>percent</unitsFamily>
          <name>deadbandPercent</name>
          <__units__>%</__units__>
          <type>Double</type>
          <value>0</value>
        </deadbandPercent>
        <peakMin>
          <unitsFamily>current</unitsFamily>
          <name>peakMin</name>
          <__units__>A</__units__>
          <type>Double</type>
          <value>0</value>
        </peakMin>
        <peakMax>
          <unitsFamily>current</unitsFamily>
          <name>peakMax</name>
          <__units__>A</__units__>
          <type>Double</type>
          <value>0</value>
        </peakMax>
      </theMotorConfigs>
      <theCurrentLimits>
        <enableStatorCurrentLimit>
          <unitsFamily>none</unitsFamily>
          <name>enableStatorCurrentLimit</name>
          <__units__ />
          <type>Boolean</type>
          <value>false</value>
        </enableStatorCurrentLimit>
        <statorCurrentLimit>
          <unitsFamily>current</unitsFamily>
          <name>statorCurrentLimit</name>
          <__units__>A</__units__>
          <type>Double</type>
          <value>0</value>
        </statorCurrentLimit>
        <enableSupplyCurrentLimit>
          <unitsFamily>none</unitsFamily>
          <name>enableSupplyCurrentLimit</name>
          <__units__ />
          <type>Boolean</type>
          <value>false</value>
        </enableSupplyCurrentLimit>
        <supplyCurrentLimit>
          <unitsFamily>current</unitsFamily>
          <name>supplyCurrentLimit</name>
          <__units__>A</__units__>
          <type>Double</type>
          <value>0</value>
        </supplyCurrentLimit>
        <supplyCurrentThreshold>
          <unitsFamily>current</unitsFamily>
          <name>supplyCurrentThreshold</name>
          <__units__>A</__units__>
          <type>Double</type>
          <value>0</value>
        </supplyCurrentThreshold>
        <supplyTimeThreshold>
          <unitsFamily>time</unitsFamily>
          <name>supplyTimeThreshold</name>
          <__units__>s</__units__>
          <type>Double</type>
          <value>0</value>
        </supplyTimeThreshold>
      </theCurrentLimits>
      <theVoltageConfigs>
        <peakForwardVoltage>
          <unitsFamily>time</unitsFamily>
          <name>peakForwardVoltage</name>
          <__units__>s</__units__>
          <type>Double</type>
          <value>0</value>
        </peakForwardVoltage>
        <peakReverseVoltage>
          <unitsFamily>time</unitsFamily>
          <name>peakReverseVoltage</name>
          <__units__>s</__units__>
          <type>Double</type>
          <value>0</value>
        </peakReverseVoltage>
        <supplyVoltageTime>
          <unitsFamily>time</unitsFamily>
          <name>supplyVoltageTime</name>
          <__units__>s</__units__>
          <type>Double</type>
          <value>0</value>
        </supplyVoltageTime>
      </theVoltageConfigs>
      <theTorqueConfigs>
        <peakForwardTorqueCurrent>
          <unitsFamily>current</unitsFamily>
          <name>peakForwardTorqueCurrent</name>
          <__units__>A</__units__>
          <type>Double</type>
          <value>0</value>
        </peakForwardTorqueCurrent>
        <peakReverseTorqueCurrent>
          <unitsFamily>current</unitsFamily>
          <name>peakReverseTorqueCurrent</name>
          <__units__>A</__units__>
          <type>Double</type>
          <value>0</value>
        </peakReverseTorqueCurrent>
        <torqueNeutralDeadband>
          <unitsFamily>current</unitsFamily>
          <name>torqueNeutralDeadband</name>
          <__units__>A</__units__>
          <type>Double</type>
          <value>0</value>
        </torqueNeutralDeadband>
      </theTorqueConfigs>
      <theFeedbackConfigs>
        <feedbackRotorOffset>
          <unitsFamily>angle</unitsFamily>
          <name>feedbackRotorOffset</name>
          <__units__>deg</__units__>
          <type>Double</type>
          <value>0</value>
        </feedbackRotorOffset>
        <remoteSensorID>
          <unitsFamily>none</unitsFamily>
          <name>remoteSensorID</name>
          <__units__ />
          <type>Int32</type>
          <value>0</value>
        </remoteSensorID>
      </theFeedbackConfigs>
    </MotorController>
  </MotorControllers>
  <closedLoopControlParameters />
  <solenoid>
    <solenoid>
      <name>solenoid_1</name>
      <CAN_ID>
        <unitsFamily>none</unitsFamily>
        <name>CAN_ID</name>
        <__units__ />
        <type>UInt32</type>
        <value>0</value>
      </CAN_ID>
      <channel>
        <unitsFamily>none</unitsFamily>
        <name>channel</name>
        <__units__ />
        <type>UInt32</type>
        <value>0</value>
      </channel>
      <enableDualChannel>
        <unitsFamily>none</unitsFamily>
        <name>enableDualChannel</name>
        <__units__ />
        <type>Boolean</type>
        <value>false</value>
      </enableDualChannel>
      <forwardChannel>
        <unitsFamily>none</unitsFamily>
        <name>forwardChannel</name>
        <__units__ />
        <type>UInt32</type>
        <value>0</value>
      </forwardChannel>
      <reverseChannel>
        <unitsFamily>none</unitsFamily>
        <name>reverseChannel</name>
        <__units__ />
        <type>UInt32</type>
        <value>0</value>
      </reverseChannel>
      <reversed>
        <unitsFamily>none</unitsFamily>
        <name>reversed</name>
        <__units__ />
        <type>Boolean</type>
        <value>false</value>
      </reversed>
    </solenoid>
    <solenoid>
      <name>solenoid_2</name>
      <CAN_ID>
        <unitsFamily>none</unitsFamily>
        <name>CAN_ID</name>
        <__units__ />
        <type>UInt32</type>
        <value>0</value>
      </CAN_ID>
      <channel>
        <unitsFamily>none</unitsFamily>
        <name>channel</name>
        <__units__ />
        <type>UInt32</type>
        <value>0</value>
      </channel>
      <enableDualChannel>
        <unitsFamily>none</unitsFamily>
        <name>enableDualChannel</name>
        <__units__ />
        <type>Boolean</type>
        <value>false</value>
      </enableDualChannel>
      <forwardChannel>
        <unitsFamily>none</unitsFamily>
        <name>forwardChannel</name>
        <__units__ />
        <type>UInt32</type>
        <value>0</value>
      </forwardChannel>
      <reverseChannel>
        <unitsFamily>none</unitsFamily>
        <name>reverseChannel</name>
        <__units__ />
        <type>UInt32</type>
        <value>0</value>
      </reverseChannel>
      <reversed>
        <unitsFamily>none</unitsFamily>
        <name>reversed</name>
        <__units__ />
        <type>Boolean</type>
        <value>false</value>
      </reversed>
    </solenoid>
  </solenoid>
  <servo>
    <servo>
      <name>servo_17</name>
      <Id>
        <unitsFamily>none</unitsFamily>
        <name>Id</name>
        <__units__ />
        <type>UInt32</type>
        <value>2</value>
      </Id>
      <minAngle>
        <unitsFamily>angle</unitsFamily>
        <name>minAngle</name>
        <__units__>deg</__units__>
        <type>Double</type>
        <value>5</value>
      </minAngle>
      <maxAngle>
        <unitsFamily>angle</unitsFamily>
        <name>maxAngle</name>
        <__units__>deg</__units__>
        <type>Double</type>
        <value>356</value>
      </maxAngle>
    </servo>
  </servo>
  <analogInput>
    <analogInput>
      <name>analogInput_1</name>
      <analogId>
        <unitsFamily>none</unitsFamily>
        <name>analogId</name>
        <__units__ />
        <type>UInt32</type>
        <value>0</value>
      </analogId>
      <voltageMin>
        <unitsFamily>none</unitsFamily>
        <name>voltageMin</name>
        <__units__ />
        <type>Double</type>
        <value>0</value>
      </voltageMin>
      <voltageMax>
        <unitsFamily>none</unitsFamily>
        <name>voltageMax</name>
        <__units__ />
        <type>Double</type>
        <value>5</value>
      </voltageMax>
      <outputMin>
        <unitsFamily>none</unitsFamily>
        <name>outputMin</name>
        <__units__ />
        <type>Double</type>
        <value>0</value>
      </outputMin>
      <outputMax>
        <unitsFamily>none</unitsFamily>
        <name>outputMax</name>
        <__units__ />
        <type>Double</type>
        <value>0</value>
      </outputMax>
    </analogInput>
  </analogInput>
  <digitalInput>
    <digitalInput>
      <name>digitalInput_1</name>
      <digitalId>
        <unitsFamily>none</unitsFamily>
        <name>digitalId</name>
        <__units__ />
        <type>UInt32</type>
        <value>0</value>
      </digitalId>
      <reversed>
        <unitsFamily>none</unitsFamily>
        <name>reversed</name>
        <__units__ />
        <type>Boolean</type>
        <value>false</value>
      </reversed>
      <debouncetime>
        <unitsFamily>time</unitsFamily>
        <name>debouncetime</name>
        <__units__>s</__units__>
        <type>Double</type>
        <value>3</value>
      </debouncetime>
    </digitalInput>
  </digitalInput>
  <cancoder />
</mechanism>